<?xml version="1.0" encoding="utf-8"?>
<search>
  
  
  
  <entry>
    <title></title>
    <link href="/2023/09/08/%E8%83%BD%E9%87%8F/"/>
    <url>/2023/09/08/%E8%83%BD%E9%87%8F/</url>
    
    <content type="html"><![CDATA[<h1 id="能量"><a href="#能量" class="headerlink" title="能量"></a>能量</h1><p>动物似乎与生俱来的都会带着能量（偏向于情绪的、心态的），尤其是体现在有脑子，有思维的动物身上，或正或负，亦正亦邪。</p><p>这种能量在人身上更是体现的淋漓尽致。饱暖思淫欲，饥寒起盗心。人在富足安逸的时候难免会生出傲慢之心，人在低迷、困顿时很难避免偏执姿态，如果沉迷其中，无法逃脱，种种恶果便会接踵而来。即使你拥有人人羡慕的容貌、博览群书的才华、挥霍不尽的财富亦难以幸免于难啊。当然，这些都是负能量，是我们不应提倡的，我们应极力克服或者说战胜它。而这一点正是这也是我们人所以区别于动物之最大特性。</p><p>那么如何战胜负能量拥抱正能量呢？其实我也不知道该怎样如何用文字描述下来。哈哈，或许就像道家的：”天机不可泄露亦或是佛教禅宗的“不立文字、不可言说”的见性成佛吧！（绝对不是应为我也不知道！）我觉得每个人都应该有自己的答案，这也是我们应该用一生去寻找，去追求的。</p><p>说实话，我一直很推崇正能量，也觉得拥有很多正能量是一件很好的事，但是事实却真的如此吗吗？我不知道，我的脑袋空空，我也一直在找答案。</p><p>后来我看到这样一句话————传言尼采曾云：我是太阳，光热无穷，只想给予，不想取得。作为enfp中的epitome，本人深有体会，很多时候会带给身边的人lopsided能量。于是我我得到一个理解尼采另外一句话“白昼之光，岂知夜色之深。”的新角度：过载的能量反而有殆。————这段话全照搬。。。</p><p>我问al这句话怎么理解，他给我的回答是：“过载的能量”可能是指你的热情、积极和能量满满的状态，而“殆”则可能指的是由于这种过载的能量，可能导致你在某些情况下过度消耗自己的精力，或者无法完全理解或者掌握某些事物的深层次含义。换句话说，你可能需要找到一个平衡点，让自己既能保持热情和积极，又能避免过度消耗自己的精力或者对某些事物理解不足。这可能需要你更好地了解自己的需求和极限，同时也需要你在不同的情况下灵活调整自己的状态和行为。</p><p>哦！这样就好理解多了，原来就是过犹不及。</p><p>突然，我脑子里想到了小的时候啊，亲戚特别特情，总是给我夹菜，我那时候又是特别内向，话到嘴边也终究是开不了口（社恐是这样的），它的热情我接受不了啊（虽然也可能是客套）。</p><p>有人为尼采哭泣：“他终究不是太阳，他不被理解，长时间的孤独、精神疾病，肺炎，最终让他失去了理智。</p><p>人们为他惋惜，他虽不是太阳，但也在人类历史上留下了浓墨重彩的一笔。</p><p>只要人类文明尚存，就一定有人记着他。</p><p>最后，我想到了儒家的核心思想中庸。中庸思想主张在处理人际关系和事务时，应避免过度极端和偏颇，寻求各方面的平衡和折中，以达到和谐的局面。</p><p>孔子曰：“中庸之为德也，其至矣乎！”  o.O? （原来中庸也和道德境界有关啊！） </p><p>在古代中庸思想包括“天人合一”的宇宙观、“中和”的人生观和“时中”的方法论。它强调人与人之间的和谐、平衡以及恰到好处的状态，倡导人们在行为和思考时应当遵循“不偏不倚、不过不及、调和折衷”的原则，以实现“万物并育而不相害，道并行而不相悖”的境界。（原来是这样啊！）</p><p>在现代社会中，中庸思想仍然具有很强的现实意义。它提醒人们在处理问题时要寻求合理的平衡点，避免过度极端和偏颇，以实现个人和社会的和谐发展。同时，中庸思想也鼓励人们保持一种平和的心态，以实现内心的平静和宁静。（中庸牛逼！(⊙o⊙)）</p><p>咳咳，扯远了，我的题目是能量。</p><p> 原来古人早就有了结论（这个能量好像写的更小丑了 (；′⌒&#96;)）。</p><p>问题不大，追求正能量，追求能量的平衡，我们需要去参悟中庸。（要靠追寻，去求索，而不是摆烂）。</p><p>如果有人说为啥我悟不透！我会说：笨比，当然是你悟性不够（bushi）。</p><p>人生路慢慢，在今天这个浮躁的社会里，人们更应该以平和的心态面对生活中的种种挑战与机遇。</p><p>共勉(ง •_•)ง</p><p>bian2</p>]]></content>
    
    
    
  </entry>
  
  
  
  <entry>
    <title></title>
    <link href="/2023/08/15/java%E5%9F%BA%E7%A1%80/"/>
    <url>/2023/08/15/java%E5%9F%BA%E7%A1%80/</url>
    
    <content type="html"><![CDATA[<p><code>8.15</code></p><p>万丈高楼平地起，跟着javasec学习</p><p>java平台共分为三个主要版本 javaSE、java EE、javaME</p><h1 id="java基础"><a href="#java基础" class="headerlink" title="java基础"></a>java基础</h1><h3 id="ClassLoader-类加载机制"><a href="#ClassLoader-类加载机制" class="headerlink" title="ClassLoader 类加载机制"></a>ClassLoader 类加载机制</h3><p>classloader作用：java类文件的加载</p><p>顶层有Bootstrap ClassLoader （引导类加载器）、Extension ClassLoader（扩展类加载器）、App ClassLoader（系统类加载器）</p><p>它的核心方法：loadClass、findClass、findloadedClass、defineClass、resolveClass</p><h3 id="java动态加载方式"><a href="#java动态加载方式" class="headerlink" title="java动态加载方式"></a>java动态加载方式</h3><p>显式、隐式</p><p>动态加载就是显式加载</p><figure class="highlight reasonml"><table><tr><td class="gutter"><pre><span class="line">1</span><br><span class="line">2</span><br><span class="line">3</span><br><span class="line">4</span><br></pre></td><td class="code"><pre><code class="hljs reasonml">例：<br><span class="hljs-keyword">class</span>.<span class="hljs-keyword">for</span><span class="hljs-constructor">Name(<span class="hljs-string">&quot;&quot;</span>)</span><br><br>this.get<span class="hljs-constructor">Class()</span>.get<span class="hljs-constructor">Classloader()</span>.loadclass<span class="hljs-literal">()</span><br></code></pre></td></tr></table></figure><p>Class&lt;?&gt;是 泛型</p><h3 id="classLoader类加载流程（难点）"><a href="#classLoader类加载流程（难点）" class="headerlink" title="classLoader类加载流程（难点）"></a>classLoader类加载流程（难点）</h3><h3 id="自定义ClassLoader"><a href="#自定义ClassLoader" class="headerlink" title="自定义ClassLoader"></a>自定义ClassLoader</h3><p>java.lang.ClassLoader </p>]]></content>
    
    
    
  </entry>
  
  
  
  <entry>
    <title></title>
    <link href="/2023/08/12/%E6%9C%89%E5%85%B3java%20web%E7%9A%84%E4%B8%80%E7%82%B9%E7%82%B9%E5%88%86%E4%BA%AB/"/>
    <url>/2023/08/12/%E6%9C%89%E5%85%B3java%20web%E7%9A%84%E4%B8%80%E7%82%B9%E7%82%B9%E5%88%86%E4%BA%AB/</url>
    
    <content type="html"><![CDATA[<h1 id="有关java-web的一点点分享"><a href="#有关java-web的一点点分享" class="headerlink" title="有关java web的一点点分享"></a>有关java web的一点点分享</h1><p>推荐一个网址：<a href="https://javasec.org/">https://javasec.org/</a></p><p>素十八：<a href="https://su18.org/post/code-audit/">https://su18.org/post/code-audit/</a>    b站：n1ar4</p><h3 id="了解Maven"><a href="#了解Maven" class="headerlink" title="了解Maven"></a>了解Maven</h3><p>1.是什么？</p><p>一个Java开发比较常用的**<u>项目管理</u>**工具 </p><p>概念：将项目开发和管理过程抽象成一个POM （Project Object Model 项目对象模型）</p><p>生命周期：<a href="https://blog.csdn.net/weixin_37799575/article/details/128843752">https://blog.csdn.net/weixin_37799575/article/details/128843752</a></p><p>2.有什么用</p><p><u>项目构建、依赖管理</u> 、统一开发结构 （方便导入jar包）</p><p>3.要了解什么</p><ul><li>Maven安装配置  <a href="https://blog.csdn.net/jianleking/article/details/109454318">https://blog.csdn.net/jianleking/article/details/109454318</a></li><li>遇到bug怎么解决  1.下载慢 2.依赖爆红线</li><li>如何加速 —镜像 </li><li>常用插件  插件：<a href="http://wed.xjx100.cn/news/220731.html?action=onClick">http://wed.xjx100.cn/news/220731.html?action=onClick</a></li><li>多模块项目</li><li>了解Gradle</li></ul><h3 id="IDEA"><a href="#IDEA" class="headerlink" title="IDEA"></a>IDEA</h3><h4 id="1-自定义搜索范围"><a href="#1-自定义搜索范围" class="headerlink" title="1.自定义搜索范围"></a>1.自定义搜索范围</h4><p>快捷键：ctrl+shirt+F</p><p><img src="https://dongzao-1314466014.cos.ap-nanjing.myqcloud.com/pic/202308121129913.webp" alt="image-20230812104805865"></p><p>IDEA可以通过自定义搜索范围来精确查找我们需要审计的代码。默认搜索的是所有的位置，不过我们可以点击红色方框的<code>...</code>按钮来细化我们的搜索范围</p><p><img src="https://dongzao-1314466014.cos.ap-nanjing.myqcloud.com/pic/202308121129536.webp" alt="image-20230812105821622"></p><p><img src="https://dongzao-1314466014.cos.ap-nanjing.myqcloud.com/pic/202308121129845.webp" alt="image-20230812105728648"></p><h4 id="2-调用链搜索"><a href="#2-调用链搜索" class="headerlink" title="2 调用链搜索"></a>2 调用链搜索</h4><p>当我们审计代码的时候发现某个方法或类有漏洞时我们需要定位到漏洞的请求地址(触发点)，复杂业务系统往往会让我们很难定位到漏洞的触发点。借助IDEA的方法调用链搜索功能就可以很轻松的找出方法的调用链和触发点。</p><p>选择<code>类或者方法名</code>–&gt;<code>右键</code>–&gt;<code>Find Useages</code>或者使用快捷键<code>alt+F7</code></p><h4 id="3-显示类的方法"><a href="#3-显示类的方法" class="headerlink" title="3 显示类的方法"></a>3 显示类的方法</h4><p>快捷键<code>ctrl+F12</code> </p><h4 id="4-显示类继承关系"><a href="#4-显示类继承关系" class="headerlink" title="4. 显示类继承关系"></a>4. 显示类继承关系</h4><p>快捷键<code>crtl+shirt+alt+U</code>或者右键</p><h4 id="5-可以自动反编译jar和class文件"><a href="#5-可以自动反编译jar和class文件" class="headerlink" title="5.可以自动反编译jar和class文件"></a>5.可以自动反编译jar和class文件</h4><p>class可以直接丢进去</p><p>jar包丢到任意目录，然后<code>右键</code>-&gt;Add as library</p><p>还有很多功能</p><h4 id="Spring-Boot自定义Banner"><a href="#Spring-Boot自定义Banner" class="headerlink" title="Spring Boot自定义Banner"></a>Spring Boot自定义Banner</h4><p>还有很多很多功能等待我们去摸索。。。</p><p>8.12</p>]]></content>
    
    
    
  </entry>
  
  
  
  <entry>
    <title></title>
    <link href="/2023/07/22/first/"/>
    <url>/2023/07/22/first/</url>
    
    <content type="html"><![CDATA[<h1 id="first-23-7-21"><a href="#first-23-7-21" class="headerlink" title="first 23.7.21"></a>first 23.7.21</h1><h2 id="一、yxcms"><a href="#一、yxcms" class="headerlink" title="一、yxcms"></a>一、yxcms</h2><h3 id="0x00-前言"><a href="#0x00-前言" class="headerlink" title="0x00.前言"></a>0x00.前言</h3><p>看了一篇php代码审计的博客，学习了一番:<a href="http://www.535yx.cn/">http://www.535yx.cn/</a></p><p>yxcms 使用的是canphp 的入门级别的MVC框架</p><p>源码下载地址：<a href="http://down.chinaz.com/soft/33853.htm">http://down.chinaz.com/soft/33853.htm</a></p><p>搭建使用的phpstudy、vscode</p><h3 id="0x01-MVC框架"><a href="#0x01-MVC框架" class="headerlink" title="0x01 MVC框架"></a>0x01 MVC框架</h3><p>Model View Controller ———模型、视图、控制器</p><p><img src="http://535yx.cn/usr/uploads/2022/11/2624244282.png" alt="80001-wvk8o6z5qmm.png"></p><h3 id="0x02-分析"><a href="#0x02-分析" class="headerlink" title="0x02 分析"></a>0x02 分析</h3><h4 id="1-结构"><a href="#1-结构" class="headerlink" title="1.结构"></a>1.结构</h4><p>看一下这个cms的结构</p><p><img src="https://dongzao-1314466014.cos.ap-nanjing.myqcloud.com/pic/202307221042197.webp" alt="image-20230721220120969"></p><p>有  data；protected；public；upload ，一看意思猜出来了 ,对外访问可以看到的就是public目录,protexted 就是不可对外</p><p>protected&#x2F;apps&#x2F;admin </p><p>下面的目录  （app是应用目录）  </p><p><img src="https://dongzao-1314466014.cos.ap-nanjing.myqcloud.com/pic/202307221042803.webp" alt="image-20230721215525868"></p><p>其实thinkphp的结构和这个也是差不多的。</p><h4 id="2-函数"><a href="#2-函数" class="headerlink" title="2.函数"></a>2.函数</h4><p>和大家复习一下php函数吧！</p><p>include(),require();fopen(),fwrite(),readfile();unlink(),eval()以及变体函数</p><p>addslashes函数可用于为存储在数据库中的字符串以及数据库查询语句准备合适的字符串。</p><p><img src="https://dongzao-1314466014.cos.ap-nanjing.myqcloud.com/pic/202307221042897.webp" alt="image-20230720104547345"></p><p>htmlspecialchars() 函数把一些预定义的字符转换为 HTML 实体。 都可以用来防止注入。</p><h3 id="0x03-审计"><a href="#0x03-审计" class="headerlink" title="0x03 审计"></a>0x03 审计</h3><p>用seay扫一下</p><p><img src="https://dongzao-1314466014.cos.ap-nanjing.myqcloud.com/pic/202307221042883.webp" alt="image-20230722103754171"></p><p>任意文件上传漏洞(protected&#x2F;apps&#x2F;appmanage&#x2F;controller&#x2F;indexController.php)</p><p><img src="https://dongzao-1314466014.cos.ap-nanjing.myqcloud.com/pic/202307221138193.webp" alt="image-20230722111836678"></p><figure class="highlight"><table><tr><td class="gutter"><pre><span class="line">1</span><br></pre></td><td class="code"><pre><code class="hljs"><br></code></pre></td></tr></table></figure><figure class="highlight php"><table><tr><td class="gutter"><pre><span class="line">1</span><br><span class="line">2</span><br><span class="line">3</span><br><span class="line">4</span><br><span class="line">5</span><br><span class="line">6</span><br><span class="line">7</span><br><span class="line">8</span><br><span class="line">9</span><br><span class="line">10</span><br><span class="line">11</span><br><span class="line">12</span><br><span class="line">13</span><br><span class="line">14</span><br><span class="line">15</span><br><span class="line">16</span><br><span class="line">17</span><br><span class="line">18</span><br><span class="line">19</span><br><span class="line">20</span><br><span class="line">21</span><br><span class="line">22</span><br><span class="line">23</span><br><span class="line">24</span><br><span class="line">25</span><br><span class="line">26</span><br><span class="line">27</span><br><span class="line">28</span><br><span class="line">29</span><br><span class="line">30</span><br><span class="line">31</span><br><span class="line">32</span><br><span class="line">33</span><br><span class="line">34</span><br><span class="line">35</span><br><span class="line">36</span><br><span class="line">37</span><br><span class="line">38</span><br><span class="line">39</span><br><span class="line">40</span><br><span class="line">41</span><br><span class="line">42</span><br><span class="line">43</span><br><span class="line">44</span><br><span class="line">45</span><br><span class="line">46</span><br><span class="line">47</span><br><span class="line">48</span><br><span class="line">49</span><br></pre></td><td class="code"><pre><code class="hljs php"><span class="hljs-comment">//导入</span><br><span class="hljs-keyword">public</span> <span class="hljs-function"><span class="hljs-keyword">function</span> <span class="hljs-title">import</span>(<span class="hljs-params"><span class="hljs-variable">$zip_file</span>=<span class="hljs-string">&#x27;&#x27;</span></span>)</span>&#123;<br><span class="hljs-keyword">if</span>(<span class="hljs-keyword">empty</span>(<span class="hljs-variable">$zip_file</span>))&#123;<br><span class="hljs-keyword">if</span>( !<span class="hljs-variable language_">$this</span>-&gt;<span class="hljs-title function_ invoke__">isPost</span>() )&#123;<br><span class="hljs-variable language_">$this</span>-&gt;<span class="hljs-title function_ invoke__">display</span>();<br><span class="hljs-keyword">return</span> <span class="hljs-literal">true</span>;<br>&#125;<br><br><span class="hljs-keyword">if</span>(<span class="hljs-variable">$_FILES</span>[<span class="hljs-string">&#x27;file&#x27;</span>][<span class="hljs-string">&#x27;size&#x27;</span>] &lt; <span class="hljs-number">0</span>)&#123;<br><span class="hljs-variable language_">$this</span>-&gt;<span class="hljs-title function_ invoke__">error</span>(<span class="hljs-string">&#x27;请选择文件&#x27;</span>);<br>&#125;<br><span class="hljs-variable">$zip_file</span> = <span class="hljs-variable">$_FILES</span>[<span class="hljs-string">&#x27;file&#x27;</span>][<span class="hljs-string">&#x27;tmp_name&#x27;</span>];<br>&#125;<br><br><span class="hljs-variable">$zip_dir</span> = BASE_PATH . <span class="hljs-string">&#x27;cache/tmp/&#x27;</span> .<span class="hljs-title function_ invoke__">md5</span>(<span class="hljs-variable">$zip_file</span>) .<span class="hljs-string">&#x27;/&#x27;</span>;<br><span class="hljs-keyword">if</span>(<span class="hljs-title function_ invoke__">substr</span>(<span class="hljs-variable">$zip_dir</span>,<span class="hljs-number">0</span>,<span class="hljs-number">1</span>)==<span class="hljs-string">&quot;/&quot;</span>)  <span class="hljs-variable">$zip_dir</span>=<span class="hljs-string">&#x27;.&#x27;</span>.<span class="hljs-variable">$zip_dir</span>; <span class="hljs-comment">//无法获得绝对路径情况</span><br><br><span class="hljs-variable">$zip</span> = <span class="hljs-keyword">new</span> <span class="hljs-title class_">Zip</span>();<br><span class="hljs-variable">$zip</span>-&gt;<span class="hljs-title function_ invoke__">decompress</span>(<span class="hljs-variable">$zip_file</span>, <span class="hljs-variable">$zip_dir</span>);<br>@<span class="hljs-title function_ invoke__">unlink</span>(<span class="hljs-variable">$zip_file</span>);<br><br><span class="hljs-comment">//获取app名称</span><br><span class="hljs-variable">$app</span> = <span class="hljs-string">&#x27;&#x27;</span>;<br><span class="hljs-variable">$arr</span> = <span class="hljs-title function_ invoke__">glob</span>(<span class="hljs-variable">$zip_dir</span> .<span class="hljs-string">&#x27;*/config.php&#x27;</span>);<br><span class="hljs-keyword">if</span>( !<span class="hljs-keyword">empty</span>(<span class="hljs-variable">$arr</span>) )&#123;<br><span class="hljs-keyword">if</span>( <span class="hljs-title function_ invoke__">preg_match</span>(<span class="hljs-string">&#x27;#/([a-z0-9]+)/config.php#&#x27;</span>, <span class="hljs-variable">$arr</span>[<span class="hljs-number">0</span>], <span class="hljs-variable">$matches</span>))&#123;<br><span class="hljs-variable">$app</span> = <span class="hljs-variable">$matches</span>[<span class="hljs-number">1</span>];<br>&#125;<br>&#125;<br><span class="hljs-keyword">if</span>( <span class="hljs-keyword">empty</span>(<span class="hljs-variable">$app</span>) )&#123;<br><span class="hljs-title function_ invoke__">del_dir</span>(<span class="hljs-variable">$zip_dir</span>);<br><span class="hljs-variable language_">$this</span>-&gt;<span class="hljs-title function_ invoke__">error</span>(<span class="hljs-string">&#x27;安装包格式错误！&#x27;</span>);<br>&#125;<br><br><span class="hljs-comment">//判断应用是否已经存在</span><br><span class="hljs-variable">$app_path</span> = BASE_PATH . <span class="hljs-string">&#x27;apps/&#x27;</span> . <span class="hljs-variable">$app</span> . <span class="hljs-string">&#x27;/&#x27;</span>;<br><span class="hljs-keyword">if</span>( <span class="hljs-title function_ invoke__">is_dir</span>(<span class="hljs-variable">$app_path</span>) )&#123;<br><span class="hljs-title function_ invoke__">del_dir</span>(<span class="hljs-variable">$zip_dir</span>);<br><span class="hljs-variable language_">$this</span>-&gt;<span class="hljs-title function_ invoke__">error</span>(<span class="hljs-variable">$app</span> .<span class="hljs-string">&#x27;应用已存在，请先卸载！&#x27;</span>);<br>&#125;<br><br><span class="hljs-comment">//将数据拷贝到apps目录</span><br><span class="hljs-title function_ invoke__">copy_dir</span>(<span class="hljs-variable">$zip_dir</span> . <span class="hljs-variable">$app</span> , <span class="hljs-variable">$app_path</span>);<br><span class="hljs-title function_ invoke__">del_dir</span>(<span class="hljs-variable">$zip_dir</span>);<br><br><span class="hljs-comment">//执行安装</span><br><span class="hljs-variable">$_GET</span>[<span class="hljs-string">&#x27;app&#x27;</span>] = <span class="hljs-variable">$app</span>;<br><span class="hljs-variable language_">$this</span>-&gt;<span class="hljs-title function_ invoke__">install</span>();<br>&#125;<br></code></pre></td></tr></table></figure><p>当上传一个zip压缩包的时候，代码会去匹配压缩包中是否存在个文件夹(命名规则为a-z0-9)，以及文件夹中是否存在config.php文件。如果不存在的话即会返回“安装包格式错误”</p><p>判断了该应用是否存在，不存在的话就将数据拷贝到apps目录中。所以我们可以构造个压缩包进行上传</p><p>压缩包里面有config.php和phpinfo</p><p><img src="https://dongzao-1314466014.cos.ap-nanjing.myqcloud.com/pic/202307221138374.webp" alt="image-20230722113614830"></p><h2 id="二、proxy代理"><a href="#二、proxy代理" class="headerlink" title="二、proxy代理"></a>二、proxy代理</h2><p>也是学习了前辈的博客 <a href="https://blog.zgsec.cn/index.php/archives/278/">https://blog.zgsec.cn/index.php/archives/278/</a></p><h3 id="一-代理vm虚拟机"><a href="#一-代理vm虚拟机" class="headerlink" title="一 代理vm虚拟机"></a>一 代理vm虚拟机</h3><h4 id="配置"><a href="#配置" class="headerlink" title="配置"></a>配置</h4><p><img src="C:\Users\33760\AppData\Roaming\Typora\typora-user-images\image-20230718110122083.png" alt="image-20230718110122083"></p><p><img src="https://dongzao-1314466014.cos.ap-nanjing.myqcloud.com/pic/202307221039183.webp" alt="image-20230718110133499"></p><p><img src="https://dongzao-1314466014.cos.ap-nanjing.myqcloud.com/pic/202307221039864.webp" alt="image-20230718110157338"></p><p>在虚拟机里面显示的</p><p>kail里面</p><p><img src="https://dongzao-1314466014.cos.ap-nanjing.myqcloud.com/pic/202307221039252.webp" alt="image-20230718110225188"></p><p>win10 </p><p><img src="https://dongzao-1314466014.cos.ap-nanjing.myqcloud.com/pic/202307221039137.webp" alt="image-20230718110356319"></p><h4 id="二-抓包小程序"><a href="#二-抓包小程序" class="headerlink" title="二 抓包小程序"></a>二 抓包小程序</h4><p><img src="https://dongzao-1314466014.cos.ap-nanjing.myqcloud.com/pic/202307221040592.webp" alt="image-20230718111256443"></p><p><img src="C:\Users\33760\AppData\Roaming\Typora\typora-user-images\image-20230718111315405.png" alt="image-20230718111315405"></p><p>配合bp</p><p><img src="https://dongzao-1314466014.cos.ap-nanjing.myqcloud.com/pic/202307221040997.webp" alt="image-20230718112448087"></p><p>三、Proxifier进行内网渗透</p><p>好像使用使用 <code>Proxifier</code> 配合Frp对相关进程进行全局代理 ，我还没学会捏！</p>]]></content>
    
    
    
  </entry>
  
  
  
  <entry>
    <title></title>
    <link href="/2023/07/22/proxy%E4%BB%A3%E7%90%86/"/>
    <url>/2023/07/22/proxy%E4%BB%A3%E7%90%86/</url>
    
    <content type="html"><![CDATA[<h1 id="proxy代理"><a href="#proxy代理" class="headerlink" title="proxy代理"></a>proxy代理</h1><h3 id="一-代理vm虚拟机"><a href="#一-代理vm虚拟机" class="headerlink" title="一 代理vm虚拟机"></a>一 代理vm虚拟机</h3><h4 id="配置"><a href="#配置" class="headerlink" title="配置"></a>配置</h4><p><img src="C:\Users\33760\AppData\Roaming\Typora\typora-user-images\image-20230718110122083.png" alt="image-20230718110122083"></p><p><img src="https://dongzao-1314466014.cos.ap-nanjing.myqcloud.com/pic/202307221039183.webp" alt="image-20230718110133499"></p><p><img src="https://dongzao-1314466014.cos.ap-nanjing.myqcloud.com/pic/202307221039864.webp" alt="image-20230718110157338"></p><p>在虚拟机里面显示的</p><p>kail里面</p><p><img src="https://dongzao-1314466014.cos.ap-nanjing.myqcloud.com/pic/202307221039252.webp" alt="image-20230718110225188"></p><p>win10 </p><p><img src="https://dongzao-1314466014.cos.ap-nanjing.myqcloud.com/pic/202307221039137.webp" alt="image-20230718110356319"></p><h4 id="二-抓包小程序"><a href="#二-抓包小程序" class="headerlink" title="二 抓包小程序"></a>二 抓包小程序</h4><p><img src="https://dongzao-1314466014.cos.ap-nanjing.myqcloud.com/pic/202307221040592.webp" alt="image-20230718111256443"></p><p><img src="C:\Users\33760\AppData\Roaming\Typora\typora-user-images\image-20230718111315405.png" alt="image-20230718111315405"></p><p><img src="https://dongzao-1314466014.cos.ap-nanjing.myqcloud.com/pic/202307221040997.webp" alt="image-20230718112448087"></p><p>三、Proxifier进行内网渗透</p><p>还没学会捏！</p>]]></content>
    
    
    
  </entry>
  
  
  
  <entry>
    <title></title>
    <link href="/2023/07/18/web%E5%89%8D%E7%AB%AF%E9%BB%91%E5%AE%A2%E6%8A%80%E6%9C%AF%E6%8F%AD%E7%A7%98/"/>
    <url>/2023/07/18/web%E5%89%8D%E7%AB%AF%E9%BB%91%E5%AE%A2%E6%8A%80%E6%9C%AF%E6%8F%AD%E7%A7%98/</url>
    
    <content type="html"><![CDATA[<h1 id="web前端黑客技术揭秘"><a href="#web前端黑客技术揭秘" class="headerlink" title="web前端黑客技术揭秘"></a>web前端黑客技术揭秘</h1><p>重视某些安全风险最好的办法就是将风险最大化</p><p><a href="https://brian3376.github.io:80/">https://brian3376.github.io:80</a> 协议、域名、端口 </p><p><scheme>:&#x2F;&#x2F;<netloc>&#x2F;<path>?<query>#<fragment></p><p>DOM 文档对象模型 Document Object Model </p><p>在web服务器上做好权限分离，防止网站和网站之间过于信任出现都被攻克（木桶理论）</p><p>web安全事件角色  w3c、浏览器厂商、web厂商、攻击者、用户</p><p>通过javascript 可以获取DOM中的隐私数据</p><p>例：document.getElementByid(‘private_msg’).innerHTML;</p><p>document.getElementByiTagName(‘div’)[2].innerHTML;</p><p>AJAX风险没搞懂</p><p>模拟用户发起游览器请求也没懂</p>]]></content>
    
    
    
  </entry>
  
  
  
  <entry>
    <title></title>
    <link href="/2023/07/13/%E5%86%85%E7%BD%91%E7%9F%A5%E8%AF%861/"/>
    <url>/2023/07/13/%E5%86%85%E7%BD%91%E7%9F%A5%E8%AF%861/</url>
    
    <content type="html"><![CDATA[<h1 id="内网"><a href="#内网" class="headerlink" title="内网"></a>内网</h1><h3 id="工作组、域环境"><a href="#工作组、域环境" class="headerlink" title="工作组、域环境"></a>工作组、域环境</h3><p>systeminfo 详细信息</p><p>net start 启动服务</p><p>tasklist  任务列表</p><p>schtasks 计划任务</p><h4 id="网络信息收集"><a href="#网络信息收集" class="headerlink" title="网络信息收集"></a>网络信息收集</h4><p>ipconfig -all 判断是否存在域-dns</p><p>net view&#x2F;domain 判断是否存在域</p><p>net time &#x2F;domain 判断主域</p><p>netstat -ano 当前网络端口开放</p><h4 id="用户信息收集"><a href="#用户信息收集" class="headerlink" title="用户信息收集"></a>用户信息收集</h4><h5 id="常见默认用户身份"><a href="#常见默认用户身份" class="headerlink" title="常见默认用户身份"></a>常见默认用户身份</h5><p>Domain Admins 域管理员</p><p>Domain Computers 域内机器</p><p>Domain Controllers 域控制器</p><p>Domain Guest 域访客；权限低</p><p>Domain users：域用户</p><p>Enterpri Admins：企业系统管理员用户</p><h5 id="相关用户收集操作命令"><a href="#相关用户收集操作命令" class="headerlink" title="相关用户收集操作命令"></a>相关用户收集操作命令</h5><p> whoami &#x2F;all 用户权限</p><p>net config workstation 登录信息</p><p> net user 本地用户</p><p>net localgroup 本地用户组</p><p>net user&#x2F;domain 获取域用户信息</p><p>net group&#x2F;domain 获取域用户组信息</p><p>wmic useraccount get&#x2F;all 涉及域用户详细信息</p><p>net group  “Domain Admins” &#x2F;domain 查询域管理员账户</p><p>net group  “Enterprise Admins” &#x2F;domain 查询管理员用户组</p><p>net group “Domain Controllers” &#x2F;domain 查询域控制器</p><h4 id="凭据信息收集"><a href="#凭据信息收集" class="headerlink" title="凭据信息收集"></a>凭据信息收集</h4><p>mimikatz（win）获取密码</p>]]></content>
    
    
    
  </entry>
  
  
  
  
</search>
